kk_brokkoli_gringotts/__init__.py
kk_brokkoli_gringotts/hello/__init__.py
kk_brokkoli_gringotts/hello/hello.py
kk_brokkoli_gringotts-0.1.0.dist-info/METADATA
kk_brokkoli_gringotts-0.1.0.dist-info/WHEEL
kk_brokkoli_gringotts-0.1.0.dist-info/RECORD
