Metadata-Version: 2.3
Name: kk-brokkoli-gringotts
Version: 0.1.0
Summary: Universal components for ai platform lumos
Author: yankang.ji
Author-email: yankang.ji@centurygame.com
Requires-Python: >=3.13
Classifier: Programming Language :: Python :: 3
Classifier: Programming Language :: Python :: 3.13
